GPUstatus/GPUstatus.py
GPUstatus/__init__.py
GPUstatus/demo_GPUstatus.py
graphicstatus-1.1.0.dist-info/LICENSE.txt
graphicstatus-1.1.0.dist-info/METADATA
graphicstatus-1.1.0.dist-info/WHEEL
graphicstatus-1.1.0.dist-info/top_level.txt
graphicstatus-1.1.0.dist-info/RECORD
