Metadata-Version: 2.1
Name: graphicstatus
Version: 1.1.0
Summary: GPUstatus is a fork of GPUtil ( https://github.com/anderskm/gputil ) 
Home-page: https://github.com/RuikangSun/gpustatus
Author: Ruikang Sun
Author-email: srk888666@qq.com
License: MIT
Keywords: gpu,utilization,load,memory,available,usage,free,select,nvidia
Classifier: Topic :: System :: Hardware :: Hardware Drivers
Classifier: License :: OSI Approved :: MIT License
Classifier: Programming Language :: Python :: 3
Classifier: Programming Language :: Python :: 3.7
Classifier: Programming Language :: Python :: 3.8
Classifier: Programming Language :: Python :: 3.9
Classifier: Programming Language :: Python :: 3.10
Requires-Python: >=3.7
License-File: LICENSE.txt
